farssh/__init__.py
farssh/__main__.py
farssh/args.py
farssh/aws.py
farssh/commands.py
farssh/const.py
farssh/ssh.py
farssh-0.5.dist-info/METADATA
farssh-0.5.dist-info/WHEEL
farssh-0.5.dist-info/entry_points.txt
farssh-0.5.dist-info/RECORD
