Metadata-Version: 2.3
Name: farssh
Version: 0.5
Summary: Secure on-demand connections into AWS VPCs
Project-URL: Homepage, https://github.com/apparentorder/farssh
Author-email: "@apparentorder" <apparentorder@neveragain.de>
License: BSD 2-clause
Keywords: aws,mysql,postgresql,proxy,rds,ssh,tunnel,vpc
Classifier: License :: OSI Approved :: BSD License
Classifier: Programming Language :: Python :: 3
Requires-Python: >=3.8
Requires-Dist: boto3
